flatex/__init__.py
flatex/__main__.py
flatex/main.py
tests/__init__.py
tests/test_flatex.py
flatex-1.1.0.dist-info/LICENSE
flatex-1.1.0.dist-info/METADATA
flatex-1.1.0.dist-info/WHEEL
flatex-1.1.0.dist-info/entry_points.txt
flatex-1.1.0.dist-info/top_level.txt
flatex-1.1.0.dist-info/RECORD
