Metadata-Version: 2.1
Name: flatex
Version: 1.1.0
Summary: A tool to flatten LaTeX files with include directives
Home-page: https://github.com/borgmanJeremy/flatex
Author: Jeremy Borgman
Author-email: borgman.jeremy@pm.me
Project-URL: Bug Tracker, https://github.com/borgmanJeremy/flatex/issues
Classifier: Programming Language :: Python :: 3
Classifier: License :: OSI Approved :: GNU General Public License v3 or later (GPLv3+)
Classifier: Operating System :: OS Independent
Classifier: Development Status :: 3 - Alpha
Requires-Python: >=3.6
License-File: LICENSE
